pairwise_correlation_miner/Pairwise_Correlation_Miner.py
pairwise_correlation_miner/__init__.py
pairwise_correlation_miner-3.1.dist-info/LICENSE
pairwise_correlation_miner-3.1.dist-info/METADATA
pairwise_correlation_miner-3.1.dist-info/WHEEL
pairwise_correlation_miner-3.1.dist-info/top_level.txt
pairwise_correlation_miner-3.1.dist-info/RECORD
