Metadata-Version: 2.1
Name: pairwise_correlation_miner
Version: 3.1
Summary: A python function to mine pairwise correlations from a dataframe with many features and targets. Exports the results to a CSV.
Home-page: https://github.com/theoregonconnection/pairwise_correlation_miner
Author: Michael McNamara
Author-email: theoregonconnection@gmail.com
Classifier: Programming Language :: Python :: 3
Classifier: License :: OSI Approved :: MIT License
Classifier: Operating System :: OS Independent
Requires-Python: >=3.6
License-File: LICENSE
Requires-Dist: pandas >=1.0.0
Requires-Dist: scipy >=1.5.0
Requires-Dist: scikit-learn >=0.23.0
